seed_vision/__init__.py
seed_vision/common/__init__.py
seed_vision/common/algebra.py
seed_vision/common/files.py
seed_vision/common/logging.py
seed_vision/common/testing.py
seed_vision/dataset/__init__.py
seed_vision/dataset/converters.py
seed_vision/dataset/converts_test.py
seed_vision/dataset/files.py
seed_vision/dataset/files_test.py
seed_vision/dataset/labelme.py
seed_vision/dataset/labels.py
seed_vision/dataset/loader.py
seed_vision/dataset/loader_test.py
seed_vision/dataset/objects.py
seed_vision/polygons/__init__.py
seed_vision/polygons/position.py
seed_vision/polygons/rectangle.py
seed_vision/polygons/segment.py
seed_vision/polygons/segment_test.py
seed_vision/presentation/draw.py
seed_vision/reference/__init__.py
seed_vision/reference/calibration.py
seed_vision/reference/calibration_test.py
seed_vision/scripts/create_yolo_dataset.py
seed_vision/segmantation/__init__.py
seed_vision/segmantation/clustering.py
seed_vision/segmantation/opencv.py
seed_vision/segmantation/opencv_test.py
seed_vision/segmantation/segment_detector.py
seed_vision-0.0.1.dist-info/LICENSE.txt
seed_vision-0.0.1.dist-info/METADATA
seed_vision-0.0.1.dist-info/WHEEL
seed_vision-0.0.1.dist-info/entry_points.txt
seed_vision-0.0.1.dist-info/top_level.txt
seed_vision-0.0.1.dist-info/RECORD
